automark-1.0.7.data/scripts/marker
marker/__init__.py
marker/commands/__init__.py
marker/commands/delete.py
marker/commands/download.py
marker/commands/prepare.py
marker/commands/run.py
marker/commands/set_status.py
marker/commands/upload_marks.py
marker/commands/upload_reports.py
marker/lms/__init__.py
marker/lms/canvas.py
marker/lms/markus.py
marker/utils/__init__.py
marker/utils/config.py
marker/utils/marksheet.py
marker/utils/tests.py
automark-1.0.7.dist-info/LICENSE
automark-1.0.7.dist-info/METADATA
automark-1.0.7.dist-info/WHEEL
automark-1.0.7.dist-info/top_level.txt
automark-1.0.7.dist-info/RECORD
