Metadata-Version: 2.1
Name: automark
Version: 1.0.7
Summary: A highly configurable auto-marker
Home-page: https://github.com/mustafaquraish/marker
Author: Mustafa Quraish
Author-email: mustafa@cs.toronto.edu
License: MIT
Platform: UNKNOWN
Classifier: Programming Language :: Python :: 3
Classifier: License :: OSI Approved :: MIT License
Classifier: Operating System :: Unix
Requires-Dist: requests
Requires-Dist: pyyaml
